ovos_hardware_helpers/__init__.py
ovos_hardware_helpers/fan.py
ovos_hardware_helpers/switches.py
ovos_hardware_helpers/version.py
ovos_hardware_helpers/led/__init__.py
ovos_hardware_helpers/led/animations.py
ovos_hardware_helpers-0.0.1.dist-info/licenses/LICENSE
ovos_hardware_helpers-0.0.1.dist-info/METADATA
ovos_hardware_helpers-0.0.1.dist-info/WHEEL
ovos_hardware_helpers-0.0.1.dist-info/top_level.txt
ovos_hardware_helpers-0.0.1.dist-info/RECORD
