Metadata-Version: 2.4
Name: ovos_hardware_helpers
Version: 0.0.1
Summary: Helper scripts for some hardware
Home-page: https://github.com/OpenVoiceOS/ovos_hardware_helpers
Author: builderjer
Author-email: builderjer@gmail.com
License: Apache-2.0
License-File: LICENSE
Requires-Dist: ovos-color-parser
Dynamic: author
Dynamic: author-email
Dynamic: description
Dynamic: description-content-type
Dynamic: home-page
Dynamic: license
Dynamic: license-file
Dynamic: requires-dist
Dynamic: summary
